breadboard_colab.py
breadboard_colab-0.0.3.dist-info/METADATA
breadboard_colab-0.0.3.dist-info/WHEEL
breadboard_colab-0.0.3.dist-info/top_level.txt
breadboard_colab-0.0.3.dist-info/RECORD
